crystal_tree/__init__.py
crystal_tree/_version.py
crystal_tree/crystal_tree.py
crystal_tree/logic_tree/__init__.py
crystal_tree/logic_tree/_logic_tree.py
crystal_tree/logic_tree/defaults_lp/__init__.py
crystal_tree/logic_tree/defaults_lp/default_extra.lp
crystal_tree/logic_tree/defaults_lp/default_feature_traces.lp
crystal_tree/logic_tree/defaults_lp/default_prediction_traces.lp
crystal_tree-0.2.dist-info/METADATA
crystal_tree-0.2.dist-info/WHEEL
crystal_tree-0.2.dist-info/top_level.txt
crystal_tree-0.2.dist-info/RECORD
