Metadata-Version: 2.1
Name: crystal-tree
Version: 0.2
Summary: From large, deep trees to short, clear explanations.
Home-page: https://github.com/bramucas/crystal-tree
Author: Brais Muñiz
Author-email: mc.brais@gmail.com
License: UNKNOWN
Keywords: artificial intelligence,explainable artificial intelligencelogic programming,answer set programming
Platform: UNKNOWN
Classifier: Programming Language :: Python :: 3
Classifier: License :: OSI Approved :: MIT License
Classifier: Operating System :: OS Independent
Requires-Python: >=3.6.0
Requires-Dist: dafact
Requires-Dist: importlib-resources
Requires-Dist: numpy
Requires-Dist: setuptools-git
Requires-Dist: sklearn
Requires-Dist: xclingo
